[
    {
        "id": 26,
        "profilePhoto":  "https://ik.imagekit.io/335jblpnu5/personality-test.png",
        "firstName": "janeasdfasdf",
        "middleName": "dialasdfasdf",
        "lastName": "2",
        "maritalStatus": "single",
        "homeAddress": "in the streets",
        "telephoneNumber": "",
        "mobileNumber": "",
        "birthDate": "01/23/2000",
        "isArchived": false
    },
    {
        "id": 9,
        "profilePhoto": "",
        "firstName": "Marwin",
        "middleName": "",
        "lastName": "Cruz",
        "maritalStatus": "Single",
        "homeAddress": "Block 321 Lot 23 Mabuhay St.",
        "telephoneNumber": "24123143",
        "mobileNumber": "09123456788",
        "birthDate": "01/02/2002",
        "isArchived": false
    },
    {
        "id": 7,
        "profilePhoto": "",
        "firstName": "Marwin",
        "middleName": "",
        "lastName": "Cruz",
        "maritalStatus": "Single",
        "homeAddress": "Block 321 Lot 23 Mabuhay St.",
        "telephoneNumber": "24123143",
        "mobileNumber": "09123456788",
        "birthDate": "01/02/2002",
        "isArchived": false
    },
    {
        "id": 8,
        "profilePhoto": "",
        "firstName": "Marwin",
        "middleName": "",
        "lastName": "Cruz",
        "maritalStatus": "Single",
        "homeAddress": "Block 321 Lot 23 Mabuhay St.",
        "telephoneNumber": "24123143",
        "mobileNumber": "09123456788",
        "birthDate": "01/02/2002",
        "isArchived": false
    },
    {
        "id": 10,
        "profilePhoto": "",
        "firstName": "Marwin",
        "middleName": "",
        "lastName": "Cruz",
        "maritalStatus": "Single",
        "homeAddress": "Block 321 Lot 23 Mabuhay St.",
        "telephoneNumber": "24123143",
        "mobileNumber": "09123456788",
        "birthDate": "01/02/2002",
        "isArchived": false
    },
    {
        "id": 4,
        "profilePhoto": "",
        "firstName": "Juan",
        "middleName": "",
        "lastName": "Dela Cruz",
        "maritalStatus": "Single",
        "homeAddress": "Block 123 Lot 23 Mabuhay St.",
        "telephoneNumber": "24123142",
        "mobileNumber": "09123456789",
        "birthDate": "01/02/2003",
        "isArchived": false
    },
    {
        "id": 6,
        "profilePhoto": "",
        "firstName": "Marwin",
        "middleName": "",
        "lastName": "Dela Cruz",
        "maritalStatus": "Single",
        "homeAddress": "Block 123 Lot 23 Mabuhay St.",
        "telephoneNumber": "24123142",
        "mobileNumber": "09123456789",
        "birthDate": "01/02/2003",
        "isArchived": false
    },
    {
        "id": 15,
        "profilePhoto": "",
        "firstName": "Lhey",
        "middleName": "Garcia",
        "lastName": "Dela Cruz",
        "maritalStatus": "Single",
        "homeAddress": "Block 321 Lot 23 Mabuhay St.",
        "telephoneNumber": "24123143",
        "mobileNumber": "09123456788",
        "birthDate": "01/02/2002",
        "isArchived": false
    },
    {
        "id": 2,
        "profilePhoto": "",
        "firstName": "Juan",
        "middleName": "",
        "lastName": "Dela Cruz",
        "maritalStatus": "Single",
        "homeAddress": "Block 123 Lot 23 Mabuhay St.",
        "telephoneNumber": "24123142",
        "mobileNumber": "09123456789",
        "birthDate": "01/02/2003",
        "isArchived": false
    },
    {
        "id": 3,
        "profilePhoto": "",
        "firstName": "Juan",
        "middleName": "",
        "lastName": "Dela Cruz",
        "maritalStatus": "Single",
        "homeAddress": "Block 123 Lot 23 Mabuhay St.",
        "telephoneNumber": "24123142",
        "mobileNumber": "09123456789",
        "birthDate": "01/02/2003",
        "isArchived": false
    },
    {
        "id": 5,
        "profilePhoto": "",
        "firstName": "Juan",
        "middleName": "",
        "lastName": "Dela Cruz",
        "maritalStatus": "Single",
        "homeAddress": "Block 123 Lot 23 Mabuhay St.",
        "telephoneNumber": "24123142",
        "mobileNumber": "09123456789",
        "birthDate": "01/02/2003",
        "isArchived": false
    },
    {
        "id": 1,
        "profilePhoto": "",
        "firstName": "Juan",
        "middleName": "",
        "lastName": "Dela Cruz",
        "maritalStatus": "Single",
        "homeAddress": "Block 123 Lot 23 Mabuhay St.",
        "telephoneNumber": "24123142",
        "mobileNumber": "09123456789",
        "birthDate": "01/02/2003",
        "isArchived": false
    },
    {
        "id": 13,
        "profilePhoto": "",
        "firstName": "Marwin",
        "middleName": "Garcia",
        "lastName": "Dela Cruz",
        "maritalStatus": "Single",
        "homeAddress": "Block 321 Lot 23 Mabuhay St.",
        "telephoneNumber": "24123143",
        "mobileNumber": "09123456788",
        "birthDate": "01/02/2002",
        "isArchived": false
    },
    {
        "id": 14,
        "profilePhoto": "",
        "firstName": "Marwin",
        "middleName": "Garcia",
        "lastName": "Dela Cruz",
        "maritalStatus": "Single",
        "homeAddress": "Block 321 Lot 23 Mabuhay St.",
        "telephoneNumber": "24123143",
        "mobileNumber": "09123456788",
        "birthDate": "01/02/2002",
        "isArchived": false
    },
    {
        "id": 12,
        "profilePhoto": "",
        "firstName": "Justine",
        "middleName": "Garcia",
        "lastName": "Dela Cruz",
        "maritalStatus": "Single",
        "homeAddress": "Block 321 Lot 23 Mabuhay St.",
        "telephoneNumber": "24123143",
        "mobileNumber": "09123456788",
        "birthDate": "01/02/2002",
        "isArchived": false
    },
    {
        "id": 38,
        "profilePhoto": null,
        "firstName": "Lheasyasdff",
        "middleName": "Garcia",
        "lastName": "Dela Cruzsad",
        "maritalStatus": "Single",
        "homeAddress": "Block 321 Lot 23 Mabuhay St.",
        "telephoneNumber": null,
        "mobileNumber": null,
        "birthDate": "01/02/2002",
        "isArchived": false
    },
    {
        "id": 37,
        "profilePhoto": null,
        "firstName": "Lheasyasdf",
        "middleName": "Garcia",
        "lastName": "Dela Cruzsad",
        "maritalStatus": "Single",
        "homeAddress": "Block 321 Lot 23 Mabuhay St.",
        "telephoneNumber": "24123143",
        "mobileNumber": "09123456788",
        "birthDate": "01/02/2002",
        "isArchived": false
    },
    {
        "id": 39,
        "profilePhoto": "",
        "firstName": "Lheasyasdffa",
        "middleName": "Garcia",
        "lastName": "Dela Cruzsad",
        "maritalStatus": "Single",
        "homeAddress": "Block 321 Lot 23 Mabuhay St.",
        "telephoneNumber": "",
        "mobileNumber": "",
        "birthDate": "01/02/2002",
        "isArchived": false
    },
    {
        "id": 36,
        "profilePhoto": null,
        "firstName": "Lheasy",
        "middleName": "Garcia",
        "lastName": "Dela Cruzsad",
        "maritalStatus": "Single",
        "homeAddress": "Block 321 Lot 23 Mabuhay St.",
        "telephoneNumber": "24123143",
        "mobileNumber": "09123456788",
        "birthDate": "01/02/2002",
        "isArchived": false
    },
    {
        "id": 18,
        "profilePhoto": "",
        "firstName": "jane",
        "middleName": "dididfa",
        "lastName": "doafo",
        "maritalStatus": "single",
        "homeAddress": "some other street",
        "telephoneNumber": "",
        "mobileNumber": "",
        "birthDate": "01/23/2001",
        "isArchived": false
    },
    {
        "id": 19,
        "profilePhoto": "",
        "firstName": "janeasdf",
        "middleName": "dididfasdf",
        "lastName": "doafoasd",
        "maritalStatus": "single",
        "homeAddress": "some other street",
        "telephoneNumber": "",
        "mobileNumber": "",
        "birthDate": "01/23/2001",
        "isArchived": false
    },
    {
        "id": 16,
        "profilePhoto": "",
        "firstName": "john",
        "middleName": "didi",
        "lastName": "doe",
        "maritalStatus": "single",
        "homeAddress": "some street",
        "telephoneNumber": "",
        "mobileNumber": "",
        "birthDate": "01/23/2001",
        "isArchived": false
    },
    {
        "id": 17,
        "profilePhoto": "https://ik.imagekit.io/335jblpnu5/test_image.png",
        "firstName": "jane",
        "middleName": "didi",
        "lastName": "doe",
        "maritalStatus": "single",
        "homeAddress": "some other address",
        "telephoneNumber": "",
        "mobileNumber": "",
        "birthDate": "01/23/2001",
        "isArchived": false
    },
    {
        "id": 27,
        "profilePhoto": "",
        "firstName": "john",
        "middleName": "didili",
        "lastName": "donks",
        "maritalStatus": "single",
        "homeAddress": "in the streets",
        "telephoneNumber": "",
        "mobileNumber": "",
        "birthDate": "01/23/2001",
        "isArchived": false
    },
    {
        "id": 21,
        "profilePhoto": "https://ik.imagekit.io/335jblpnu5/profile.png",
        "firstName": "jane",
        "middleName": "dial",
        "lastName": "donks",
        "maritalStatus": "single",
        "homeAddress": "in the streets",
        "telephoneNumber": "",
        "mobileNumber": "",
        "birthDate": "01/23/2000",
        "isArchived": false
    },
    {
        "id": 28,
        "profilePhoto": "",
        "firstName": "john",
        "middleName": "didili",
        "lastName": "donksaa",
        "maritalStatus": "single",
        "homeAddress": "in the streets",
        "telephoneNumber": "",
        "mobileNumber": "",
        "birthDate": "01/23/2001",
        "isArchived": false
    },
    {
        "id": 23,
        "profilePhoto": "https://ik.imagekit.io/335jblpnu5/personality-test.png",
        "firstName": "janeasdf",
        "middleName": "dialasdf",
        "lastName": "donksasdf",
        "maritalStatus": "single",
        "homeAddress": "in the streets",
        "telephoneNumber": "",
        "mobileNumber": "",
        "birthDate": "01/23/2000",
        "isArchived": false
    },
    {
        "id": 22,
        "profilePhoto": "https://ik.imagekit.io/335jblpnu5/personality-test.png",
        "firstName": "janeasdf",
        "middleName": "dialasdf",
        "lastName": "donksasdf",
        "maritalStatus": "single",
        "homeAddress": "in the streets",
        "telephoneNumber": "",
        "mobileNumber": "",
        "birthDate": "01/23/2000",
        "isArchived": false
    },
    {
        "id": 24,
        "profilePhoto": "https://ik.imagekit.io/335jblpnu5/personality-test.png",
        "firstName": "janeasdfasdf",
        "middleName": "dialasdfasdf",
        "lastName": "donksasdfdsaf",
        "maritalStatus": "single",
        "homeAddress": "in the streets",
        "telephoneNumber": "",
        "mobileNumber": "",
        "birthDate": "01/23/2000",
        "isArchived": false
    },
    {
        "id": 25,
        "profilePhoto": "https://ik.imagekit.io/335jblpnu5/personality-test.png",
        "firstName": "janeasdfasdf",
        "middleName": "dialasdfasdf",
        "lastName": "donksasdfdsaf",
        "maritalStatus": "single",
        "homeAddress": "in the streets",
        "telephoneNumber": "",
        "mobileNumber": "",
        "birthDate": "01/23/2000",
        "isArchived": false
    },
    {
        "id": 20,
        "profilePhoto": "",
        "firstName": "testFirst",
        "middleName": "testMiddle",
        "lastName": "testLast",
        "maritalStatus": "single",
        "homeAddress": "some other street",
        "telephoneNumber": "",
        "mobileNumber": "",
        "birthDate": "01/23/2001",
        "isArchived": false
    }
]